scibench/__init__.py
scibench/__main__.py
scibench/experiment.py
scibench/helpers.py
scibench/registry.py
scibench-0.0.1.dist-info/LICENSE
scibench-0.0.1.dist-info/WHEEL
scibench-0.0.1.dist-info/METADATA
scibench-0.0.1.dist-info/RECORD
