Metadata-Version: 2.1
Name: scibench
Version: 0.0.1
Summary: A Python project template.
Home-page: https://marcofavorito.me/scibench
License: GPL-3.0-or-later
Author: Marco Favorito
Author-email: marco.favorito@gmail.com
Requires-Python: >=3.8,<4.0
Classifier: Development Status :: 2 - Pre-Alpha
Classifier: Intended Audience :: Developers
Classifier: License :: OSI Approved :: GNU General Public License v3 or later (GPLv3+)
Classifier: License :: OSI Approved :: GNU Lesser General Public License v3 or later (LGPLv3+)
Classifier: Natural Language :: English
Classifier: Programming Language :: Python :: 3
Classifier: Programming Language :: Python :: 3.10
Classifier: Programming Language :: Python :: 3.8
Classifier: Programming Language :: Python :: 3.9
Requires-Dist: GitPython (>=3.1.27,<4.0.0)
Requires-Dist: PyYAML (>=6.0,<7.0)
Requires-Dist: joblib (>=1.1.0,<2.0.0)
Project-URL: Bug Tracker, https://github.com/marcofavorito/scibench/issues
Project-URL: Documentation, https://marcofavorito.me/scibench
Project-URL: Pull Requests, https://github.com/marcofavorito/scibench/pulls
Project-URL: Repository, https://github.com/marcofavorito/scibench.git
